lofi/__about__.py
lofi/__init__.py
lofi-0.0.1.dist-info/METADATA
lofi-0.0.1.dist-info/WHEEL
lofi-0.0.1.dist-info/licenses/LICENSE.txt
lofi-0.0.1.dist-info/RECORD
